{
  "updatedAt": "2026-06-01T12:47:51.109Z",
  "total": 80,
  "items": [
    {
      "source": "CoinDesk",
      "title": "Live markets: bitcoin retreats under $72,000 as Strategy unloads BTC for first time in four years",
      "summary": "Crypto markets continue to struggle even as risk markets across the globe surge higher.",
      "url": "https://www.coindesk.com/markets/2026/06/01/live-markets-bitcoin-retreats-under-usd72-000-as-strategy-unloads-btc-for-first-time-in-four-years",
      "publishedAt": "2026-06-01T12:29:14.000Z",
      "keywords": [
        "Markets",
        "Live News",
        "live_news"
      ],
      "category": "市场",
      "slug": "20260601-live-markets-bitcoin-retreats-under-72000-as-strategy-unloads-btc-for-first-time",
      "localUrl": "/news/20260601-live-markets-bitcoin-retreats-under-72000-as-strategy-unloads-btc-for-first-time.html"
    },
    {
      "source": "Decrypt",
      "title": "Michael Saylor's Bitcoin Treasury Firm Strategy Sells 32 BTC for $2.5M",
      "summary": "Bitcoin tumbled to $72,000 Monday as news of the BTC treasury firm's about-face on its \"never sell\" stance broke.",
      "url": "https://decrypt.co/369587/michael-saylors-bitcoin-treasury-firm-strategy-sells-32-btc-for-2-5m",
      "publishedAt": "2026-06-01T12:22:16.000Z",
      "keywords": [
        "Markets"
      ],
      "category": "RWA",
      "slug": "20260601-michael-saylors-bitcoin-treasury-firm-strategy-sells-32-btc-for-25m",
      "localUrl": "/news/20260601-michael-saylors-bitcoin-treasury-firm-strategy-sells-32-btc-for-25m.html"
    },
    {
      "source": "CoinDesk",
      "title": "Bitcoin below $72,000 as Strategy sold 32 bitcoin sale for $2.5 million in late May",
      "summary": "The 8-K filing Monday says proceeds from the May 26-31 sale, executed at an average price of $77,135 a coin, will fund distributions on Strategy's preferred stock.",
      "url": "https://www.coindesk.com/markets/2026/06/01/strategy-sold-32-btc-for-usd2-5-million-in-late-may-filing-shows",
      "publishedAt": "2026-06-01T12:07:17.000Z",
      "keywords": [
        "Markets",
        "News"
      ],
      "category": "市场",
      "slug": "20260601-bitcoin-below-72000-as-strategy-sold-32-bitcoin-sale-for-25-million-in-late-may",
      "localUrl": "/news/20260601-bitcoin-below-72000-as-strategy-sold-32-bitcoin-sale-for-25-million-in-late-may.html"
    },
    {
      "source": "Cointelegraph",
      "title": "Bitcoin ETPs post largest 2026 outflow as crypto funds bleed $1.67B",
      "summary": "Crypto ETPs see $1.67 billion in outflows as the US dominates selling, Bitcoin funds log a record 2026 exit, and altcoin participation narrows sharply across markets, according to CoinShares.",
      "url": "https://cointelegraph.com/news/crypto-etps-bleed-1-67-billion-altcoin-participation-collapse?utm_source=rss_feed&utm_medium=rss&utm_campaign=rss_partner_inbound",
      "publishedAt": "2026-06-01T11:50:13.000Z",
      "keywords": [
        "Latest News"
      ],
      "category": "市场",
      "slug": "20260601-bitcoin-etps-post-largest-2026-outflow-as-crypto-funds-bleed-167b",
      "localUrl": "/news/20260601-bitcoin-etps-post-largest-2026-outflow-as-crypto-funds-bleed-167b.html"
    },
    {
      "source": "Decrypt",
      "title": "Bitcoin ETF Losses Near $3B Across 10 Days as YTD Flows Turn Negative",
      "summary": "U.S. spot Bitcoin ETFs extended their outflow streak to 10 days, as crypto markets contend with multiple simultaneous headwinds.",
      "url": "https://decrypt.co/369583/bitcoin-etf-losses-near-3b-across-10-days-as-ytd-flows-turn-negative",
      "publishedAt": "2026-06-01T11:46:35.000Z",
      "keywords": [
        "Markets"
      ],
      "category": "监管",
      "slug": "20260601-bitcoin-etf-losses-near-3b-across-10-days-as-ytd-flows-turn-negative",
      "localUrl": "/news/20260601-bitcoin-etf-losses-near-3b-across-10-days-as-ytd-flows-turn-negative.html"
    },
    {
      "source": "Cointelegraph",
      "title": "Binance adds US stock trading in push beyond crypto",
      "summary": "Binance launched US equities trading for eligible users and plans tokenized stocks as crypto exchanges expand into broader financial markets.",
      "url": "https://cointelegraph.com/news/binance-launches-tokenized-stocks-245-trading?utm_source=rss_feed&utm_medium=rss&utm_campaign=rss_partner_inbound",
      "publishedAt": "2026-06-01T11:30:08.000Z",
      "keywords": [
        "Latest News"
      ],
      "category": "RWA",
      "slug": "20260601-binance-adds-us-stock-trading-in-push-beyond-crypto",
      "localUrl": "/news/20260601-binance-adds-us-stock-trading-in-push-beyond-crypto.html"
    },
    {
      "source": "Cointelegraph",
      "title": "ECB official says stablecoins risk importing old market flaws",
      "summary": "ECB board member Isabel Schnabel warned that stablecoins could bring money-market risks into tokenized finance and reinforce US dollar dominance.",
      "url": "https://cointelegraph.com/news/ecb-stablecoins-public-money-digital-euro?utm_source=rss_feed&utm_medium=rss&utm_campaign=rss_partner_inbound",
      "publishedAt": "2026-06-01T11:21:55.000Z",
      "keywords": [
        "Latest News"
      ],
      "category": "监管",
      "slug": "20260601-ecb-official-says-stablecoins-risk-importing-old-market-flaws",
      "localUrl": "/news/20260601-ecb-official-says-stablecoins-risk-importing-old-market-flaws.html"
    },
    {
      "source": "Decrypt",
      "title": "Coinbase Launches Direct Indian Rupee Deposit and Withdrawal Rails",
      "summary": "The U.S. exchange has established direct rupee trading rails for Indian customers after securing regulatory clearance.",
      "url": "https://decrypt.co/369580/coinbase-launches-direct-indian-rupee-deposit-and-withdrawal-rails",
      "publishedAt": "2026-06-01T11:11:26.000Z",
      "keywords": [
        "Business"
      ],
      "category": "监管",
      "slug": "20260601-coinbase-launches-direct-indian-rupee-deposit-and-withdrawal-rails",
      "localUrl": "/news/20260601-coinbase-launches-direct-indian-rupee-deposit-and-withdrawal-rails.html"
    },
    {
      "source": "CoinDesk",
      "title": "Cardano Summit 2026 canceled after community votes against Foundation funding proposal",
      "summary": "The Cardano Foundation's flagship conference was scrapped after a funding proposal failed to secure the two-thirds support required under the blockchain's new governance system.",
      "url": "https://www.coindesk.com/markets/2026/06/01/cardano-governance-vote-kills-summit-approves-smaller-token2049-plan",
      "publishedAt": "2026-06-01T10:46:51.000Z",
      "keywords": [
        "Finance",
        "Cardano",
        "News"
      ],
      "category": "监管",
      "slug": "20260601-cardano-summit-2026-canceled-after-community-votes-against-foundation-funding-pr",
      "localUrl": "/news/20260601-cardano-summit-2026-canceled-after-community-votes-against-foundation-funding-pr.html"
    },
    {
      "source": "CoinDesk",
      "title": "Strategy holds STRC dividend at 11.5% for fourth straight month",
      "summary": "The preferred stock remains near its $100 par value as the company balances yield stability, ATM issuance capacity, and its bitcoin acquisition strategy.",
      "url": "https://www.coindesk.com/markets/2026/06/01/strategy-holds-strc-dividend-at-11-5-for-fourth-straight-month",
      "publishedAt": "2026-06-01T10:37:27.000Z",
      "keywords": [
        "Markets",
        "Bitcoin News",
        "MicroStrategy",
        "News"
      ],
      "category": "DeFi",
      "slug": "20260601-strategy-holds-strc-dividend-at-115-for-fourth-straight-month",
      "localUrl": "/news/20260601-strategy-holds-strc-dividend-at-115-for-fourth-straight-month.html"
    },
    {
      "source": "CoinDesk",
      "title": "Bitcoin, ether start June in the red while futures show taste for risk. XLM, HYPE gain",
      "summary": "Bitcoin and ether fell Monday after dropping in May, a month that usually sees them post positive returns. U.S. equity index futures rose.",
      "url": "https://www.coindesk.com/markets/2026/06/01/bitcoin-ether-start-june-in-the-red-while-futures-show-taste-for-risk-xlm-hype-gain",
      "publishedAt": "2026-06-01T10:04:10.000Z",
      "keywords": [
        "Markets",
        "Crypto Markets Today",
        "News"
      ],
      "category": "DeFi",
      "slug": "20260601-bitcoin-ether-start-june-in-the-red-while-futures-show-taste-for-risk-xlm-hype-g",
      "localUrl": "/news/20260601-bitcoin-ether-start-june-in-the-red-while-futures-show-taste-for-risk-xlm-hype-g.html"
    },
    {
      "source": "CoinDesk",
      "title": "Bitcoin and software stocks are breaking up — and history says a major crypto move is coming",
      "summary": "Bitcoin and software equities have sharply diverged after moving in lockstep for years, raising questions over whether bitcoin will eventually catch up.",
      "url": "https://www.coindesk.com/markets/2026/06/01/software-stocks-break-from-bitcoin-as-igv-stages-powerful-recovery",
      "publishedAt": "2026-06-01T10:02:58.000Z",
      "keywords": [
        "Markets",
        "Bitcoin News",
        "News"
      ],
      "category": "市场",
      "slug": "20260601-bitcoin-and-software-stocks-are-breaking-up-and-history-says-a-major-crypto-move",
      "localUrl": "/news/20260601-bitcoin-and-software-stocks-are-breaking-up-and-history-says-a-major-crypto-move.html"
    },
    {
      "source": "Decrypt",
      "title": "What Is BChat? The Decentralized Messaging App Built for Privacy",
      "summary": "Built on the Beldex Network, BChat aims to solve the weaknesses of relying solely on end-to-end encryption (E2EE) for private messaging.",
      "url": "https://decrypt.co/resources/what-is-bchat-beldex-decentralized-messaging-app-privacy",
      "publishedAt": "2026-06-01T10:01:04.000Z",
      "keywords": [
        "The Projects"
      ],
      "category": "DeFi",
      "slug": "20260601-what-is-bchat-the-decentralized-messaging-app-built-for-privacy",
      "localUrl": "/news/20260601-what-is-bchat-the-decentralized-messaging-app-built-for-privacy.html"
    },
    {
      "source": "Cointelegraph",
      "title": "Coinbase launches rupee bank rails in India after FIU nod",
      "summary": "Coinbase has switched on direct rupee bank transfers in India via IMPS, letting users move funds between local bank accounts and the exchange for spot and futures trading.",
      "url": "https://cointelegraph.com/news/coinbase-rolls-out-rupee-bank-rails-in-india-after-watchdog-approval?utm_source=rss_feed&utm_medium=rss&utm_campaign=rss_partner_inbound",
      "publishedAt": "2026-06-01T09:45:49.000Z",
      "keywords": [
        "Latest News"
      ],
      "category": "综合",
      "slug": "20260601-coinbase-launches-rupee-bank-rails-in-india-after-fiu-nod",
      "localUrl": "/news/20260601-coinbase-launches-rupee-bank-rails-in-india-after-fiu-nod.html"
    },
    {
      "source": "Cointelegraph",
      "title": "Trump says Iran will ‘work out well’: Five things to know in Bitcoin this week",
      "summary": "Bitcoin price headed below $72,000 on Iran woes as US President Donald Trump told observers to \"sit back and relax\" with a ceasefire still unresolved.",
      "url": "https://cointelegraph.com/markets/trump-says-iran-will-work-out-well-five-things-to-know-in-bitcoin-this-week?utm_source=rss_feed&utm_medium=rss&utm_campaign=rss_partner_inbound",
      "publishedAt": "2026-06-01T08:56:01.000Z",
      "keywords": [
        "Markets"
      ],
      "category": "市场",
      "slug": "20260601-trump-says-iran-will-work-out-well-five-things-to-know-in-bitcoin-this-week",
      "localUrl": "/news/20260601-trump-says-iran-will-work-out-well-five-things-to-know-in-bitcoin-this-week.html"
    },
    {
      "source": "CoinDesk",
      "title": "U.S. Congress returns as GENIUS comments periods close, jobs report: Crypto Week Ahead",
      "summary": "Your look at what's coming in the week starting June 1.",
      "url": "https://www.coindesk.com/markets/2026/06/01/u-s-congress-returns-as-genius-comments-periods-close-jobs-report-crypto-week-ahead",
      "publishedAt": "2026-06-01T08:50:45.000Z",
      "keywords": [
        "Markets",
        "week ahead",
        "News"
      ],
      "category": "市场",
      "slug": "20260601-us-congress-returns-as-genius-comments-periods-close-jobs-report-crypto-week-ahe",
      "localUrl": "/news/20260601-us-congress-returns-as-genius-comments-periods-close-jobs-report-crypto-week-ahe.html"
    },
    {
      "source": "X Wire",
      "title": "#Bitcoin is going for my main scenario for entries from a day-trading perspective. A sweep of the lows and a reversal back upwards would be great to look for an entry when it flips the level back. I don't think we'll continue to fall, so this remains my primary scena - x.com",
      "summary": "<a href=\"https://news.google.com/rss/articles/CBMiY0FVX3lxTE9aVnFPa29jQWZYaFBVZjNleG8xWmd3bHNqajh3b0tLMXRrOHVzS1ZXbk1FSGFBUU5nQWlKZEFXdXlBdHE5U0libGJUY0hIc2tpUEt0blZsNWcyV09xZHI0amtUcw?oc=5\" target=\"_blank\">#Bitcoin is going for my main sc…",
      "url": "https://news.google.com/rss/articles/CBMiY0FVX3lxTE9aVnFPa29jQWZYaFBVZjNleG8xWmd3bHNqajh3b0tLMXRrOHVzS1ZXbk1FSGFBUU5nQWlKZEFXdXlBdHE5U0libGJUY0hIc2tpUEt0blZsNWcyV09xZHI0amtUcw?oc=5",
      "publishedAt": "2026-06-01T08:00:00.000Z",
      "keywords": [],
      "category": "X热点",
      "slug": "20260601-bitcoin-is-going-for-my-main-scenario-for-entries-from-a-day-trading-perspective",
      "localUrl": "/news/20260601-bitcoin-is-going-for-my-main-scenario-for-entries-from-a-day-trading-perspective.html"
    },
    {
      "source": "X Wire",
      "title": "BREAKING: PUBLIC COMMENT PERIOD ON RULE TO ALLOW #BITCOIN IN EVERY US 401(K) OFFICIALLY CLOSES TODAY $13 TRILLION IN RETIREMENT SAVINGS IS HEADING FOR BTC TIGHTEN YOUR SEATBELTS 🚀 - x.com",
      "summary": "<a href=\"https://news.google.com/rss/articles/CBMiYkFVX3lxTE1MUFVBTF95aGVkUFF2WkdJcmRTYkpCY3R1RWY2OFRldDRlM3pVcmZMc096Mlc4ZkFwLVpPbWEzM09IT1ZxQWZNeU5pbkp0ZElua0hTbW5uQ0ZPX21CZFJCeFZR?oc=5\" target=\"_blank\">BREAKING: PUBLIC COMMENT PERIOD ON…",
      "url": "https://news.google.com/rss/articles/CBMiYkFVX3lxTE1MUFVBTF95aGVkUFF2WkdJcmRTYkpCY3R1RWY2OFRldDRlM3pVcmZMc096Mlc4ZkFwLVpPbWEzM09IT1ZxQWZNeU5pbkp0ZElua0hTbW5uQ0ZPX21CZFJCeFZR?oc=5",
      "publishedAt": "2026-06-01T07:36:37.000Z",
      "keywords": [],
      "category": "X热点",
      "slug": "20260601-breaking-public-comment-period-on-rule-to-allow-bitcoin-in-every-us-401k-officia",
      "localUrl": "/news/20260601-breaking-public-comment-period-on-rule-to-allow-bitcoin-in-every-us-401k-officia.html"
    },
    {
      "source": "X Wire",
      "title": "Bitcoin closed May at $73,568 Market is 50/50 on if Febryary $60k was the bottom, or the bear will continue. IMO data is telling us that we have not seen bottom formation yet, and that there is a >50% probablility that we go lower (below 200wma $61k or realize - x.com",
      "summary": "<a href=\"https://news.google.com/rss/articles/CBMiZkFVX3lxTE9wZGNUOFlwcF81SW5FR3czRFF2TmRHMkpPdWM3ZlZvOFdYaG1Fam12SDNJV0xRRTVlZjBLTlhpSDgyVGJsbVctTWZzWmlaUFR1LS01ejZHRWltVFZieGQyYjFNYm80dw?oc=5\" target=\"_blank\">Bitcoin closed May at $73,56…",
      "url": "https://news.google.com/rss/articles/CBMiZkFVX3lxTE9wZGNUOFlwcF81SW5FR3czRFF2TmRHMkpPdWM3ZlZvOFdYaG1Fam12SDNJV0xRRTVlZjBLTlhpSDgyVGJsbVctTWZzWmlaUFR1LS01ejZHRWltVFZieGQyYjFNYm80dw?oc=5",
      "publishedAt": "2026-06-01T07:30:16.000Z",
      "keywords": [],
      "category": "X热点",
      "slug": "20260601-bitcoin-closed-may-at-73568-market-is-5050-on-if-febryary-60k-was-the-bottom-or-",
      "localUrl": "/news/20260601-bitcoin-closed-may-at-73568-market-is-5050-on-if-febryary-60k-was-the-bottom-or-.html"
    },
    {
      "source": "Cointelegraph",
      "title": "NYDIG suggests $1.3B IBIT sale was whale exiting directional trade",
      "summary": "NYDIG’s Greg Cipolaro says a sale below market price and giving up millions of dollars for immediate execution indicates a large directional holder exited a trade on BlackRock’s IBIT last week.",
      "url": "https://cointelegraph.com/news/nydig-ibit-whale-exit-directional-bitcoin-trade?utm_source=rss_feed&utm_medium=rss&utm_campaign=rss_partner_inbound",
      "publishedAt": "2026-06-01T07:09:14.000Z",
      "keywords": [
        "Latest News"
      ],
      "category": "市场",
      "slug": "20260601-nydig-suggests-13b-ibit-sale-was-whale-exiting-directional-trade",
      "localUrl": "/news/20260601-nydig-suggests-13b-ibit-sale-was-whale-exiting-directional-trade.html"
    },
    {
      "source": "CoinDesk",
      "title": "Citi predicts the tokenized securities market will grow to $5.5 trillion by 2030",
      "summary": "Stablecoins alone will generate a demand for up to $1 trillion worth of onchain U.S. Treasury bills and $2.6 trillion for tokenized stocks, said Citi.",
      "url": "https://www.coindesk.com/markets/2026/06/01/citi-predicts-the-tokenized-securities-market-will-grow-to-usd5-5-trillion-by-2030",
      "publishedAt": "2026-06-01T06:57:05.000Z",
      "keywords": [
        "Markets",
        "Tokenization",
        "News"
      ],
      "category": "监管",
      "slug": "20260601-citi-predicts-the-tokenized-securities-market-will-grow-to-55-trillion-by-2030",
      "localUrl": "/news/20260601-citi-predicts-the-tokenized-securities-market-will-grow-to-55-trillion-by-2030.html"
    },
    {
      "source": "CoinDesk",
      "title": "Whitehat developer unlocks $2 million stuck in a 2016 Ethereum ICO contract for nine years",
      "summary": "0xflorent, a security researcher, found an integer-overflow flaw in the HongCoin token sale contract that lets the team unlock funds for 48 original investors. It is the second such recovery he has publicized in eight days.",
      "url": "https://www.coindesk.com/tech/2026/06/01/whitehat-developer-unlocks-usd2-million-stuck-in-a-2016-ethereum-ico-contract-for-nine-years",
      "publishedAt": "2026-06-01T06:52:38.000Z",
      "keywords": [
        "Tech",
        "News"
      ],
      "category": "监管",
      "slug": "20260601-whitehat-developer-unlocks-2-million-stuck-in-a-2016-ethereum-ico-contract-for-n",
      "localUrl": "/news/20260601-whitehat-developer-unlocks-2-million-stuck-in-a-2016-ethereum-ico-contract-for-n.html"
    },
    {
      "source": "Cointelegraph",
      "title": "Sui Foundation says ‘major upgrade’ fixed bugs behind three outages",
      "summary": "The Sui Network's first two outages were caused by bugs introduced in its 1.72 update, while an interim fix deployed to restore the blockchain triggered the third.",
      "url": "https://cointelegraph.com/news/sui-major-upgrade-fixes-outage-bugs-restores-network?utm_source=rss_feed&utm_medium=rss&utm_campaign=rss_partner_inbound",
      "publishedAt": "2026-06-01T06:48:04.000Z",
      "keywords": [
        "Latest News"
      ],
      "category": "基础设施",
      "slug": "20260601-sui-foundation-says-major-upgrade-fixed-bugs-behind-three-outages",
      "localUrl": "/news/20260601-sui-foundation-says-major-upgrade-fixed-bugs-behind-three-outages.html"
    },
    {
      "source": "Cointelegraph",
      "title": "Crypto exploit losses in May fall 90% over month to $68M: CertiK",
      "summary": "CertiK says May is the third month so far in 2026 to record crypto losses under $100 million.",
      "url": "https://cointelegraph.com/news/crypto-exploit-losses-fall-by-90-in-may-to-68m-certik?utm_source=rss_feed&utm_medium=rss&utm_campaign=rss_partner_inbound",
      "publishedAt": "2026-06-01T06:40:42.000Z",
      "keywords": [
        "Latest News"
      ],
      "category": "安全",
      "slug": "20260601-crypto-exploit-losses-in-may-fall-90-over-month-to-68m-certik",
      "localUrl": "/news/20260601-crypto-exploit-losses-in-may-fall-90-over-month-to-68m-certik.html"
    },
    {
      "source": "Cointelegraph",
      "title": "Cardano Foundation cancels annual conference after failed funding vote",
      "summary": "Cardano Foundation has failed at its second attempt to secure funding from Cardano’s community to fund its annual conference.",
      "url": "https://cointelegraph.com/news/cardano-foundation-cancels-annual-conference-after-failed-funding-vote?utm_source=rss_feed&utm_medium=rss&utm_campaign=rss_partner_inbound",
      "publishedAt": "2026-06-01T06:24:07.000Z",
      "keywords": [
        "Latest News"
      ],
      "category": "监管",
      "slug": "20260601-cardano-foundation-cancels-annual-conference-after-failed-funding-vote",
      "localUrl": "/news/20260601-cardano-foundation-cancels-annual-conference-after-failed-funding-vote.html"
    },
    {
      "source": "X Wire",
      "title": "Multicoin Co-founder Kyle Samani: Web3 Is Dead, Only DeFi and DePIN Remain Forward Industries Chairman and Multicoin co-founder Kyle Samani commented, “Web3 is dead. All we have is DeFi and DePIN.” Earlier, StarkWare CEO and Zcash/StarkWare - x.com",
      "summary": "<a href=\"https://news.google.com/rss/articles/CBMiY0FVX3lxTFBDRVhnd3FnNm90SFZhSmoyZzhBMkdpMmNyb0U4R1pJcmREZmU3SXN2akVfSG9URHZuWHFqVV83OEQ1clZraDRjaXRMME1jUWpLZE83N2R4aWgzRnNGWGp6R3Jvbw?oc=5\" target=\"_blank\">Multicoin Co-founder Kyle Samani…",
      "url": "https://news.google.com/rss/articles/CBMiY0FVX3lxTFBDRVhnd3FnNm90SFZhSmoyZzhBMkdpMmNyb0U4R1pJcmREZmU3SXN2akVfSG9URHZuWHFqVV83OEQ1clZraDRjaXRMME1jUWpLZE83N2R4aWgzRnNGWGp6R3Jvbw?oc=5",
      "publishedAt": "2026-06-01T06:19:49.000Z",
      "keywords": [],
      "category": "X热点",
      "slug": "20260601-multicoin-co-founder-kyle-samani-web3-is-dead-only-defi-and-depin-remain-forward",
      "localUrl": "/news/20260601-multicoin-co-founder-kyle-samani-web3-is-dead-only-defi-and-depin-remain-forward.html"
    },
    {
      "source": "X Wire",
      "title": "Long-term holding trends suggest Bitcoin is increasingly being treated as a store of value. Supply is steadily concentrating in long-held positions over time. ₿ - x.com",
      "summary": "<a href=\"https://news.google.com/rss/articles/CBMiXEFVX3lxTE1SZDhrZXBzbHNRRXZiUzNDYnpPbkJRRkwwLURSeWRXY29hSUwtVW03dlN1ZkZQMFpzbGJwZThLYllwSkNGSTlXRjZiRXQ5Z1NSVXBQSUFQdVRrajRv?oc=5\" target=\"_blank\">Long-term holding trends suggest Bitcoin i…",
      "url": "https://news.google.com/rss/articles/CBMiXEFVX3lxTE1SZDhrZXBzbHNRRXZiUzNDYnpPbkJRRkwwLURSeWRXY29hSUwtVW03dlN1ZkZQMFpzbGJwZThLYllwSkNGSTlXRjZiRXQ5Z1NSVXBQSUFQdVRrajRv?oc=5",
      "publishedAt": "2026-06-01T06:02:54.000Z",
      "keywords": [],
      "category": "X热点",
      "slug": "20260601-long-term-holding-trends-suggest-bitcoin-is-increasingly-being-treated-as-a-stor",
      "localUrl": "/news/20260601-long-term-holding-trends-suggest-bitcoin-is-increasingly-being-treated-as-a-stor.html"
    },
    {
      "source": "CoinDesk",
      "title": "XRP drops to $1.32 as sellers overpower exchange outflows",
      "summary": "XRP hit a 15-week low before stabilizing, with traders watching whether the latest washout turns into a base or another leg lower.",
      "url": "https://www.coindesk.com/markets/2026/06/01/xrp-drops-to-usd1-32-as-sellers-overpower-exchange-outflows",
      "publishedAt": "2026-06-01T05:41:31.000Z",
      "keywords": [
        "Markets",
        "XRP News",
        "News"
      ],
      "category": "市场",
      "slug": "20260601-xrp-drops-to-132-as-sellers-overpower-exchange-outflows",
      "localUrl": "/news/20260601-xrp-drops-to-132-as-sellers-overpower-exchange-outflows.html"
    },
    {
      "source": "CoinDesk",
      "title": "Three Sui mainnet halts in 48 hours traced to an upgrade bug by developers",
      "summary": "The Sui Foundation's post-mortem published Sunday traces all three outages to interactions between a new address-balance feature shipped in the v1.72 release and the network's existing gas and consensus logic.",
      "url": "https://www.coindesk.com/tech/2026/06/01/three-sui-mainnet-halts-in-48-hours-traced-to-an-upgrade-bug-by-developers",
      "publishedAt": "2026-06-01T05:38:50.000Z",
      "keywords": [
        "Tech",
        "News"
      ],
      "category": "基础设施",
      "slug": "20260601-three-sui-mainnet-halts-in-48-hours-traced-to-an-upgrade-bug-by-developers",
      "localUrl": "/news/20260601-three-sui-mainnet-halts-in-48-hours-traced-to-an-upgrade-bug-by-developers.html"
    },
    {
      "source": "CoinDesk",
      "title": "Bitcoin extends slide as spot ETF outflows hit a record while Wall Street rips on AI",
      "summary": "U.S. spot bitcoin ETFs lost $2.97 billion across 10 trading days through Friday, the longest outflow streak on record. Oil's bounce on the stalled Iran deal added pressure even as global equities hit new highs on the Nvidia and SoftBank AI…",
      "url": "https://www.coindesk.com/markets/2026/06/01/bitcoin-extends-slide-as-spot-etf-outflows-hit-a-record-while-wall-street-rips-on-ai",
      "publishedAt": "2026-06-01T05:11:40.000Z",
      "keywords": [
        "Markets",
        "News"
      ],
      "category": "监管",
      "slug": "20260601-bitcoin-extends-slide-as-spot-etf-outflows-hit-a-record-while-wall-street-rips-o",
      "localUrl": "/news/20260601-bitcoin-extends-slide-as-spot-etf-outflows-hit-a-record-while-wall-street-rips-o.html"
    },
    {
      "source": "CoinDesk",
      "title": "Aave overhauls listing standards after $230 million rsETH exploit exposed bridge risks",
      "summary": "An official postmortem traced the exploit to a LayerZero bridge verification failure and outlined a sweeping overhaul of Aave's asset-listing standards as DeFi risks shift beyond smart contract bugs.",
      "url": "https://www.coindesk.com/markets/2026/06/01/aave-overhauls-listing-standards-after-usd230-million-rseth-exploit-exposed-bridge-risks",
      "publishedAt": "2026-06-01T05:04:17.000Z",
      "keywords": [
        "Markets",
        "News"
      ],
      "category": "安全",
      "slug": "20260601-aave-overhauls-listing-standards-after-230-million-rseth-exploit-exposed-bridge-",
      "localUrl": "/news/20260601-aave-overhauls-listing-standards-after-230-million-rseth-exploit-exposed-bridge-.html"
    },
    {
      "source": "X Wire",
      "title": "The Clarity Act is not just a crypto bill. It's a decision about whether America leads the next financial system or watches from the sidelines. - x.com",
      "summary": "<a href=\"https://news.google.com/rss/articles/CBMiX0FVX3lxTFA1WkFlNHB5X1Y4OU1yeFI5ZmxlR29KRkFNamNJQUphbUVZcFZiNnZvLVR1SHFRTG9nVEpRTDU1OWcxUXFYMEJmSFZQclFaaXBUNWRqYmkzbzMzR0RiZGVz?oc=5\" target=\"_blank\">The Clarity Act is not just a crypto b…",
      "url": "https://news.google.com/rss/articles/CBMiX0FVX3lxTFA1WkFlNHB5X1Y4OU1yeFI5ZmxlR29KRkFNamNJQUphbUVZcFZiNnZvLVR1SHFRTG9nVEpRTDU1OWcxUXFYMEJmSFZQclFaaXBUNWRqYmkzbzMzR0RiZGVz?oc=5",
      "publishedAt": "2026-06-01T04:29:00.000Z",
      "keywords": [],
      "category": "X热点",
      "slug": "20260601-the-clarity-act-is-not-just-a-crypto-bill-its-a-decision-about-whether-america-l",
      "localUrl": "/news/20260601-the-clarity-act-is-not-just-a-crypto-bill-its-a-decision-about-whether-america-l.html"
    },
    {
      "source": "Cointelegraph",
      "title": "Wintermute to bring liquidity to booming prediction markets sector",
      "summary": "Wintermute said it will provide “two-sided markets across event contracts on leading venues,” but did not specify what platforms it was trading on.",
      "url": "https://cointelegraph.com/news/wintermute-is-entering-prediction-markets-as-a-liquidity-provider?utm_source=rss_feed&utm_medium=rss&utm_campaign=rss_partner_inbound",
      "publishedAt": "2026-06-01T04:22:38.000Z",
      "keywords": [
        "Latest News"
      ],
      "category": "监管",
      "slug": "20260601-wintermute-to-bring-liquidity-to-booming-prediction-markets-sector",
      "localUrl": "/news/20260601-wintermute-to-bring-liquidity-to-booming-prediction-markets-sector.html"
    },
    {
      "source": "Cointelegraph",
      "title": "White hat hacker recovers $2M from faulty 2016 ICO smart contract",
      "summary": "A white-hat hacker has helped the creators of Hong Coin by showing them how to exploit a flawed admin function on a smart contract and ultimately refund investors after a decade.",
      "url": "https://cointelegraph.com/news/whitehat-helps-recover-2m-from-2016-ico-smart-contract?utm_source=rss_feed&utm_medium=rss&utm_campaign=rss_partner_inbound",
      "publishedAt": "2026-06-01T02:21:56.000Z",
      "keywords": [
        "Latest News"
      ],
      "category": "监管",
      "slug": "20260601-white-hat-hacker-recovers-2m-from-faulty-2016-ico-smart-contract",
      "localUrl": "/news/20260601-white-hat-hacker-recovers-2m-from-faulty-2016-ico-smart-contract.html"
    },
    {
      "source": "CoinDesk",
      "title": "Coinbase makes a major play for India’s booming $3 billion crypto market with local currency launch",
      "summary": "Coinbase announces INR rails to make the platform fully accessible to Indian retail traders.",
      "url": "https://www.coindesk.com/markets/2026/05/31/coinbase-makes-a-major-play-for-india-s-booming-usd3-billion-crypto-market-with-local-currency-launch",
      "publishedAt": "2026-05-31T23:30:00.000Z",
      "keywords": [
        "Markets",
        "Coinbase",
        "Markets",
        "India",
        "News"
      ],
      "category": "市场",
      "slug": "20260531-coinbase-makes-a-major-play-for-indias-booming-3-billion-crypto-market-with-loca",
      "localUrl": "/news/20260531-coinbase-makes-a-major-play-for-indias-booming-3-billion-crypto-market-with-loca.html"
    },
    {
      "source": "Cointelegraph",
      "title": "US, UK central bankers offer contrary views on stablecoins",
      "summary": "Federal Reserve Governor Christopher Waller told a conference on Sunday that stablecoins expand the reach of US policy while the Bank of England’s Megan Greene expects their popularity will soon fade.",
      "url": "https://cointelegraph.com/news/us-uk-central-bankers-offer-contrary-views-on-stablecoins?utm_source=rss_feed&utm_medium=rss&utm_campaign=rss_partner_inbound",
      "publishedAt": "2026-05-31T21:11:35.000Z",
      "keywords": [
        "Latest News"
      ],
      "category": "监管",
      "slug": "20260531-us-uk-central-bankers-offer-contrary-views-on-stablecoins",
      "localUrl": "/news/20260531-us-uk-central-bankers-offer-contrary-views-on-stablecoins.html"
    },
    {
      "source": "Cointelegraph",
      "title": "Strategy's Michael Saylor teases BTC buy with 'working better' tweet",
      "summary": "Strategy may be set to announce it has resumed buying Bitcoin after pausing in recent weeks as the biggest crypto looks poised to close out the month down more than 3.5%.",
      "url": "https://cointelegraph.com/news/strategys-michael-saylor-says-working-better-tees-up-btc-buy?utm_source=rss_feed&utm_medium=rss&utm_campaign=rss_partner_inbound",
      "publishedAt": "2026-05-31T20:00:12.000Z",
      "keywords": [
        "Latest News"
      ],
      "category": "市场",
      "slug": "20260531-strategys-michael-saylor-teases-btc-buy-with-working-better-tweet",
      "localUrl": "/news/20260531-strategys-michael-saylor-teases-btc-buy-with-working-better-tweet.html"
    },
    {
      "source": "CoinDesk",
      "title": "A massive $1.26 billion sale of BlackRock’s IBIT was likely a rapid exit by a large investor",
      "summary": "NYDIG, meanwhile, rejected the basis-trade theory, citing the large discount and the lack of an unusual spike in corresponding CME bitcoin futures volume.",
      "url": "https://www.coindesk.com/markets/2026/05/31/a-massive-usd1-26-billion-sale-of-blackrock-s-ibit-was-likely-a-rapid-exit-by-a-large-investor",
      "publishedAt": "2026-05-31T19:41:51.000Z",
      "keywords": [
        "Markets",
        "Bitcoin News",
        "ETFs",
        "News"
      ],
      "category": "监管",
      "slug": "20260531-a-massive-126-billion-sale-of-blackrocks-ibit-was-likely-a-rapid-exit-by-a-large",
      "localUrl": "/news/20260531-a-massive-126-billion-sale-of-blackrocks-ibit-was-likely-a-rapid-exit-by-a-large.html"
    },
    {
      "source": "CoinDesk",
      "title": "How the House Financial Services Committee is taking on tokenization: State of Crypto",
      "summary": "Rep. French Hill, head of the House Financial Services Committee, weighed in on outstanding policy issues in an interview with CoinDesk last month.",
      "url": "https://www.coindesk.com/policy/2026/05/31/how-the-house-financial-services-committee-is-taking-on-tokenization-state-of-crypto",
      "publishedAt": "2026-05-31T18:30:00.000Z",
      "keywords": [
        "Policy",
        "Newsletters",
        "State of Crypto",
        "News"
      ],
      "category": "监管",
      "slug": "20260531-how-the-house-financial-services-committee-is-taking-on-tokenization-state-of-cr",
      "localUrl": "/news/20260531-how-the-house-financial-services-committee-is-taking-on-tokenization-state-of-cr.html"
    },
    {
      "source": "Cointelegraph",
      "title": "Kraken ‘plans’ regulated perp contracts as rivals are quick off blocks",
      "summary": "In the wake of CFTC approval of perpetual futures contracts tied to the spot price of Bitcoin, Kraken expects to offer those to US institutional clients within \"the next month.\"",
      "url": "https://cointelegraph.com/news/kraken-plans-regulated-perp-contracts-as-rivals-are-quick-off-the-blocks?utm_source=rss_feed&utm_medium=rss&utm_campaign=rss_partner_inbound",
      "publishedAt": "2026-05-31T17:40:00.000Z",
      "keywords": [
        "Latest News"
      ],
      "category": "基础设施",
      "slug": "20260531-kraken-plans-regulated-perp-contracts-as-rivals-are-quick-off-blocks",
      "localUrl": "/news/20260531-kraken-plans-regulated-perp-contracts-as-rivals-are-quick-off-blocks.html"
    },
    {
      "source": "CoinDesk",
      "title": "How Stellar became part of DTCC's tokenization push for Wall Street securities onchain",
      "summary": "Wall Street's clearing giant chose a public blockchain with compliance tools built for regulated assets, Stellar Development Foundation CEO Denelle Dixon said.",
      "url": "https://www.coindesk.com/business/2026/05/31/how-stellar-became-part-of-dtcc-s-tokenization-push-for-wall-street-securities-onchain",
      "publishedAt": "2026-05-31T17:00:00.000Z",
      "keywords": [
        "Finance",
        "Tokenization",
        "News"
      ],
      "category": "监管",
      "slug": "20260531-how-stellar-became-part-of-dtccs-tokenization-push-for-wall-street-securities-on",
      "localUrl": "/news/20260531-how-stellar-became-part-of-dtccs-tokenization-push-for-wall-street-securities-on.html"
    },
    {
      "source": "X Wire",
      "title": "BITCOIN DEVELOPER BURAK UNVEILS “CUBE” BTC LAYER 2, CALLS IT THE “HOLY GRAIL” Burak, known for highlighting flaws in Lightning and later creating the Layer 2 called Ark, unveils a new project called Cube. Cube is a Bitcoin-native execution lay - x.com",
      "summary": "<a href=\"https://news.google.com/rss/articles/CBMiZkFVX3lxTE8tRG4wZlFCQW01d1JvbWptNGxZYUVBcUYxVnNwZnd5cjZQb1luMXBEWXBqM1ItaW41bUN0RkZVZlBSSTJ6aENvbUNBSlpNVkxFb3pRUWtlR19QcnBubFlGUlM1aXJNZw?oc=5\" target=\"_blank\">BITCOIN DEVELOPER BURAK UNVE…",
      "url": "https://news.google.com/rss/articles/CBMiZkFVX3lxTE8tRG4wZlFCQW01d1JvbWptNGxZYUVBcUYxVnNwZnd5cjZQb1luMXBEWXBqM1ItaW41bUN0RkZVZlBSSTJ6aENvbUNBSlpNVkxFb3pRUWtlR19QcnBubFlGUlM1aXJNZw?oc=5",
      "publishedAt": "2026-05-31T16:59:04.000Z",
      "keywords": [],
      "category": "X热点",
      "slug": "20260531-bitcoin-developer-burak-unveils-cube-btc-layer-2-calls-it-the-holy-grail-burak-k",
      "localUrl": "/news/20260531-bitcoin-developer-burak-unveils-cube-btc-layer-2-calls-it-the-holy-grail-burak-k.html"
    },
    {
      "source": "Cointelegraph",
      "title": "Bitcoin preps 3% May downside, but US PMI data may boost BTC price",
      "summary": "Bitcoin faced ending May lower by around 3%, with the possibility of US PMI data giving BTC price action a boost next week.",
      "url": "https://cointelegraph.com/markets/bitcoin-price-preps-3-may-downside-as-us-pmi-data-preps-potential-btc-price-boost?utm_source=rss_feed&utm_medium=rss&utm_campaign=rss_partner_inbound",
      "publishedAt": "2026-05-31T16:39:40.000Z",
      "keywords": [
        "Markets"
      ],
      "category": "市场",
      "slug": "20260531-bitcoin-preps-3-may-downside-but-us-pmi-data-may-boost-btc-price",
      "localUrl": "/news/20260531-bitcoin-preps-3-may-downside-but-us-pmi-data-may-boost-btc-price.html"
    },
    {
      "source": "Decrypt",
      "title": "How President Trump’s Immigration Order Will Feed the Stablecoin Economy, Bitcoin ATMs",
      "summary": "When the Trump family faced pressure from banks, it embraced crypto. Now, immigrants who are in the U.S. illegally face a similar choice.",
      "url": "https://decrypt.co/369479/how-president-trump-immigration-order-feed-stablecoin-bitcoin-atms",
      "publishedAt": "2026-05-31T15:49:18.000Z",
      "keywords": [
        "Long Reads"
      ],
      "category": "市场",
      "slug": "20260531-how-president-trumps-immigration-order-will-feed-the-stablecoin-economy-bitcoin-",
      "localUrl": "/news/20260531-how-president-trumps-immigration-order-will-feed-the-stablecoin-economy-bitcoin-.html"
    },
    {
      "source": "CoinDesk",
      "title": "The institutional edge: moomoo targets Wall Street-grade trading tools for retail crypto investors",
      "summary": "The brokerage giant says the future of investing won’t be defined by asset access alone but by the quality of tools investors get.",
      "url": "https://www.coindesk.com/business/2026/05/28/the-institutional-edge-moomoo-pushes-to-offer-wall-street-grade-crypto-tools-to-retail-investors",
      "publishedAt": "2026-05-31T15:00:00.000Z",
      "keywords": [
        "Finance",
        "Crypto Trading",
        "Exclusive",
        "Moomoo",
        "News"
      ],
      "category": "DeFi",
      "slug": "20260531-the-institutional-edge-moomoo-targets-wall-street-grade-trading-tools-for-retail",
      "localUrl": "/news/20260531-the-institutional-edge-moomoo-targets-wall-street-grade-trading-tools-for-retail.html"
    },
    {
      "source": "Cointelegraph",
      "title": "Here’s what happened in crypto today",
      "summary": "Need to know what happened in crypto today? Here is the latest news on daily trends and events impacting Bitcoin price, blockchain, DeFi, Web3 and crypto regulation.",
      "url": "https://cointelegraph.com/news/what-happened-in-crypto-today?utm_source=rss_feed&utm_medium=rss&utm_campaign=rss_partner_inbound",
      "publishedAt": "2026-05-31T14:10:00.000Z",
      "keywords": [
        "Trump memecoin",
        "Solana memecoin",
        "TRUMP token",
        "Solana",
        "SOL",
        "Nova Labs",
        "SEC",
        "Securities and Exchange Commission",
        "Crypto regulation",
        "TRUMP rally",
        "Bitcoin",
        "Latest News"
      ],
      "category": "监管",
      "slug": "20260531-heres-what-happened-in-crypto-today",
      "localUrl": "/news/20260531-heres-what-happened-in-crypto-today.html"
    },
    {
      "source": "X Wire",
      "title": "JUST IN: Michael Saylor hints at buying more Bitcoin. \"Working ₿etter.\" - x.com",
      "summary": "<a href=\"https://news.google.com/rss/articles/CBMiYkFVX3lxTE43S3hlX2Nfa1pFd0tjMWdWMTh5eWpYLVBRT1M1dWZkMTJWV0dmXzJReEJTOHVjTkJKWU5UUENpVS1VUlpPeWZNamo0Nk8xZk5JbllPRks5bTE5eTRsVDR4UWhB?oc=5\" target=\"_blank\">JUST IN: Michael Saylor hints at b…",
      "url": "https://news.google.com/rss/articles/CBMiYkFVX3lxTE43S3hlX2Nfa1pFd0tjMWdWMTh5eWpYLVBRT1M1dWZkMTJWV0dmXzJReEJTOHVjTkJKWU5UUENpVS1VUlpPeWZNamo0Nk8xZk5JbllPRks5bTE5eTRsVDR4UWhB?oc=5",
      "publishedAt": "2026-05-31T13:20:22.000Z",
      "keywords": [],
      "category": "X热点",
      "slug": "20260531-just-in-michael-saylor-hints-at-buying-more-bitcoin-working-etter-xcom",
      "localUrl": "/news/20260531-just-in-michael-saylor-hints-at-buying-more-bitcoin-working-etter-xcom.html"
    },
    {
      "source": "X Wire",
      "title": "JUST IN: Michael Saylor hints that Strategy bought more bitcoin 🚀 - x.com",
      "summary": "<a href=\"https://news.google.com/rss/articles/CBMiZ0FVX3lxTE0xMDM4VDIzS09BODhORVVzZDdncUZOUldFV0YyWmJOV1MzVnMwTGhjcVdIMmNRZmZmV2hPRktJOEIxbGJUZ2l0QjM4MWdwSGZ3cFRkc3Q2UHAzOTVOUHFyUXMwVVRJcWM?oc=5\" target=\"_blank\">JUST IN: Michael Saylor hin…",
      "url": "https://news.google.com/rss/articles/CBMiZ0FVX3lxTE0xMDM4VDIzS09BODhORVVzZDdncUZOUldFV0YyWmJOV1MzVnMwTGhjcVdIMmNRZmZmV2hPRktJOEIxbGJUZ2l0QjM4MWdwSGZ3cFRkc3Q2UHAzOTVOUHFyUXMwVVRJcWM?oc=5",
      "publishedAt": "2026-05-31T13:07:40.000Z",
      "keywords": [],
      "category": "X热点",
      "slug": "20260531-just-in-michael-saylor-hints-that-strategy-bought-more-bitcoin-xcom",
      "localUrl": "/news/20260531-just-in-michael-saylor-hints-that-strategy-bought-more-bitcoin-xcom.html"
    },
    {
      "source": "CoinDesk",
      "title": "Bitcoin's wild days are over — and Trace Mayer says that's a good thing",
      "summary": "The creator of the Mayer Multiple argues bitcoin’s growing economic substance is compressing volatility and attracting deeper capital.",
      "url": "https://www.coindesk.com/markets/2026/05/28/dnp-trace-mayer-bitcoin-s-volatility-compression-is-a-sign-of-maturity-not-weakness",
      "publishedAt": "2026-05-31T13:00:00.000Z",
      "keywords": [
        "Markets",
        "Bitcoin News",
        "News"
      ],
      "category": "市场",
      "slug": "20260531-bitcoins-wild-days-are-over-and-trace-mayer-says-thats-a-good-thing",
      "localUrl": "/news/20260531-bitcoins-wild-days-are-over-and-trace-mayer-says-thats-a-good-thing.html"
    },
    {
      "source": "Cointelegraph",
      "title": "Bitcoin price targets $78K as BTC holders defend 'strongest near-term support'",
      "summary": "Bitcoin’s bounce from a key holder cost-basis level has improved the case for further upside, with historical data pointing to $101,000 as a potential best-case target.",
      "url": "https://cointelegraph.com/markets/bitcoin-price-rebound-targets-78k-as-short-term-holders-defend-support?utm_source=rss_feed&utm_medium=rss&utm_campaign=rss_partner_inbound",
      "publishedAt": "2026-05-31T12:39:47.000Z",
      "keywords": [
        "Markets"
      ],
      "category": "市场",
      "slug": "20260531-bitcoin-price-targets-78k-as-btc-holders-defend-strongest-near-term-support",
      "localUrl": "/news/20260531-bitcoin-price-targets-78k-as-btc-holders-defend-strongest-near-term-support.html"
    },
    {
      "source": "Cointelegraph",
      "title": "Vietnam proposes allowing SMEs to use digital assets as loan collateral",
      "summary": "Vietnam’s Ministry of Finance has proposed letting SMEs use digital assets, virtual assets and intellectual property as loan collateral.",
      "url": "https://cointelegraph.com/news/vietnam-proposes-allowing-smes-to-use-digital-assets-as-loan-collateral?utm_source=rss_feed&utm_medium=rss&utm_campaign=rss_partner_inbound",
      "publishedAt": "2026-05-31T10:03:56.000Z",
      "keywords": [
        "Latest News"
      ],
      "category": "综合",
      "slug": "20260531-vietnam-proposes-allowing-smes-to-use-digital-assets-as-loan-collateral",
      "localUrl": "/news/20260531-vietnam-proposes-allowing-smes-to-use-digital-assets-as-loan-collateral.html"
    },
    {
      "source": "Cointelegraph",
      "title": "Cosmos-based Gravity Bridge halts bridge after reported $5.4M exploit",
      "summary": "Gravity Bridge was drained of roughly $5.4 million in a suspected signing key compromise, prompting validators to halt the bridge while an investigation is underway.",
      "url": "https://cointelegraph.com/news/cosmos-based-gravity-bridge-halts-bridge-after-reported-54m-exploit?utm_source=rss_feed&utm_medium=rss&utm_campaign=rss_partner_inbound",
      "publishedAt": "2026-05-31T08:57:25.000Z",
      "keywords": [
        "Latest News"
      ],
      "category": "安全",
      "slug": "20260531-cosmos-based-gravity-bridge-halts-bridge-after-reported-54m-exploit",
      "localUrl": "/news/20260531-cosmos-based-gravity-bridge-halts-bridge-after-reported-54m-exploit.html"
    },
    {
      "source": "Cointelegraph",
      "title": "Bitcoin sentiment reaches most ‘lopsided positive’ ratio for 2026: Santiment",
      "summary": "Crypto sentiment platform Santiment warned that the two biggest spikes in social media bullishness around Bitcoin have previously been followed by short-term price pullbacks.",
      "url": "https://cointelegraph.com/news/crypto-sentiment-reaches-most-lopsided-positive-ratio-for-2026-santiment?utm_source=rss_feed&utm_medium=rss&utm_campaign=rss_partner_inbound",
      "publishedAt": "2026-05-31T06:02:05.000Z",
      "keywords": [
        "Latest News"
      ],
      "category": "市场",
      "slug": "20260531-bitcoin-sentiment-reaches-most-lopsided-positive-ratio-for-2026-santiment",
      "localUrl": "/news/20260531-bitcoin-sentiment-reaches-most-lopsided-positive-ratio-for-2026-santiment.html"
    },
    {
      "source": "CoinDesk",
      "title": "XRP Ledger's new proposal blocks the flash loan attacks costing DeFi hundreds of millions",
      "summary": "A draft XRPL amendment notes that flash loan attacks are \"structurally impossible\" on the network because of how its transactions are built, an architectural quirk that has spared the chain from the exploit class that has cost Ethereum DeF…",
      "url": "https://www.coindesk.com/tech/2026/05/29/xrp-ledger-s-new-proposal-blocks-the-flash-loan-attacks-costing-defi-hundreds-of-millions",
      "publishedAt": "2026-05-31T02:30:00.000Z",
      "keywords": [
        "Tech",
        "News"
      ],
      "category": "安全",
      "slug": "20260531-xrp-ledgers-new-proposal-blocks-the-flash-loan-attacks-costing-defi-hundreds-of-",
      "localUrl": "/news/20260531-xrp-ledgers-new-proposal-blocks-the-flash-loan-attacks-costing-defi-hundreds-of-.html"
    },
    {
      "source": "X Wire",
      "title": "Are you getting desperate, lad? Maybe keep your crypto millions for something else. 😂 - x.com",
      "summary": "<a href=\"https://news.google.com/rss/articles/CBMiZEFVX3lxTE9Ca196QUhmVl9maGd4VUFxU3lmZVFJMGt3bVNrc0k5Q0JTOE5vZW1ZWjRnUmx1eDRvWWp0aFl2dEl6Q3lfTzZFTlNWNnI1Vm8xZFhBQTZSb3VfZmxuUDZLY3RBZmI?oc=5\" target=\"_blank\">Are you getting desperate, lad?…",
      "url": "https://news.google.com/rss/articles/CBMiZEFVX3lxTE9Ca196QUhmVl9maGd4VUFxU3lmZVFJMGt3bVNrc0k5Q0JTOE5vZW1ZWjRnUmx1eDRvWWp0aFl2dEl6Q3lfTzZFTlNWNnI1Vm8xZFhBQTZSb3VfZmxuUDZLY3RBZmI?oc=5",
      "publishedAt": "2026-05-30T19:30:50.000Z",
      "keywords": [],
      "category": "X热点",
      "slug": "20260530-are-you-getting-desperate-lad-maybe-keep-your-crypto-millions-for-something-else",
      "localUrl": "/news/20260530-are-you-getting-desperate-lad-maybe-keep-your-crypto-millions-for-something-else.html"
    },
    {
      "source": "X Wire",
      "title": "THE FOUNDER OF ETHEREUM IS WARNING. THE MARKET IS SPRINTING THE OTHER WAY. 🇺🇸 Vitalik Buterin warns crypto dies fast if it stays about gambling with no real-world use. He's not predicting it. He's describing what already happened. Pumpfun. - x.com",
      "summary": "<a href=\"https://news.google.com/rss/articles/CBMiZEFVX3lxTE90MFYxYndYdWttT3VNQWk1QXBycktONlBoLXFWeHVBeHRnMG5ST0VBcGF4Y0JPNzkyMHBqdXFNWlh6Z0hKdWFLdTNWcGcwblRxM1Q0Q0IyQnBQQXRVUXdsSzRDSUo?oc=5\" target=\"_blank\">THE FOUNDER OF ETHEREUM IS WARN…",
      "url": "https://news.google.com/rss/articles/CBMiZEFVX3lxTE90MFYxYndYdWttT3VNQWk1QXBycktONlBoLXFWeHVBeHRnMG5ST0VBcGF4Y0JPNzkyMHBqdXFNWlh6Z0hKdWFLdTNWcGcwblRxM1Q0Q0IyQnBQQXRVUXdsSzRDSUo?oc=5",
      "publishedAt": "2026-05-30T16:30:00.000Z",
      "keywords": [],
      "category": "X热点",
      "slug": "20260530-the-founder-of-ethereum-is-warning-the-market-is-sprinting-the-other-way-vitalik",
      "localUrl": "/news/20260530-the-founder-of-ethereum-is-warning-the-market-is-sprinting-the-other-way-vitalik.html"
    },
    {
      "source": "Decrypt",
      "title": "Florida Candidate Liquidates $800K in Bitcoin to Bankroll Congressional Bid",
      "summary": "A Republican candidate jockeying to represent Florida’s 22nd Congressional District liquidated Bitcoin to help fuel his political bid.",
      "url": "https://decrypt.co/369478/florida-candidate-liquidates-800k-bitcoin-bankroll-congressional-bid",
      "publishedAt": "2026-05-30T15:44:30.000Z",
      "keywords": [
        "Law and Order"
      ],
      "category": "监管",
      "slug": "20260530-florida-candidate-liquidates-800k-in-bitcoin-to-bankroll-congressional-bid",
      "localUrl": "/news/20260530-florida-candidate-liquidates-800k-in-bitcoin-to-bankroll-congressional-bid.html"
    },
    {
      "source": "Decrypt",
      "title": "What Is an AI Prompt Injection Attack? The Hidden Threat Hijacking Your Chatbots",
      "summary": "Hackers can hijack ChatGPT, Claude, and Gemini with nothing but a sentence. OpenAI says the problem may never be fully solved. Here is what it is, how it works, and how to stay safe.",
      "url": "https://decrypt.co/resources/what-is-ai-prompt-injection-attack",
      "publishedAt": "2026-05-30T13:01:03.000Z",
      "keywords": [
        "Artificial Intelligence"
      ],
      "category": "安全",
      "slug": "20260530-what-is-an-ai-prompt-injection-attack-the-hidden-threat-hijacking-your-chatbots",
      "localUrl": "/news/20260530-what-is-an-ai-prompt-injection-attack-the-hidden-threat-hijacking-your-chatbots.html"
    },
    {
      "source": "X Wire",
      "title": "Ethereum is not a company. It is global infrastructure controlled by no entity or consortium — like the Internet That’s why institutions bring the most assets onto Ethereum ETH is not a stock or valued on fees ETH is productive money — and that’s the exponential - x.com",
      "summary": "<a href=\"https://news.google.com/rss/articles/CBMiZEFVX3lxTE9USW91ZUhCRmwzQ0dhTzdVVmNmLW5kai1GWmRqcFEyazdrbUVxQXVTeG5vOGNyaWZaRm9JdFVON1ZCaFBvelg4QjZzbXpDY0JSSUR2N1dRdzc4VmdObXRPOE9KWlU?oc=5\" target=\"_blank\">Ethereum is not a company. It i…",
      "url": "https://news.google.com/rss/articles/CBMiZEFVX3lxTE9USW91ZUhCRmwzQ0dhTzdVVmNmLW5kai1GWmRqcFEyazdrbUVxQXVTeG5vOGNyaWZaRm9JdFVON1ZCaFBvelg4QjZzbXpDY0JSSUR2N1dRdzc4VmdObXRPOE9KWlU?oc=5",
      "publishedAt": "2026-05-30T11:59:15.000Z",
      "keywords": [],
      "category": "X热点",
      "slug": "20260530-ethereum-is-not-a-company-it-is-global-infrastructure-controlled-by-no-entity-or",
      "localUrl": "/news/20260530-ethereum-is-not-a-company-it-is-global-infrastructure-controlled-by-no-entity-or.html"
    },
    {
      "source": "X Wire",
      "title": "JUST IN: ethereum:0x514910771af9ca656af840dff83e8264ecf986ca futures now trade 24/7 on @CMEGroup, the world's largest CFTC-regulated derivatives exchange. This milestone unlocks enhanced institutional access and reflects the growing maturity of - x.com",
      "summary": "<a href=\"https://news.google.com/rss/articles/CBMiX0FVX3lxTE9RUmJUcFA3cmJMTzZ6QkE4cjF3Y0tUdFV3ekFhX094dlVhSmFGcnFzSThPMkt3S2hZNEgyT0RMOFV1eFE5RGZpR1ItaVEwUGVORlpHajRsTVpMRUhYd1NN?oc=5\" target=\"_blank\">JUST IN: ethereum:0x514910771af9ca656a…",
      "url": "https://news.google.com/rss/articles/CBMiX0FVX3lxTE9RUmJUcFA3cmJMTzZ6QkE4cjF3Y0tUdFV3ekFhX094dlVhSmFGcnFzSThPMkt3S2hZNEgyT0RMOFV1eFE5RGZpR1ItaVEwUGVORlpHajRsTVpMRUhYd1NN?oc=5",
      "publishedAt": "2026-05-29T21:32:46.000Z",
      "keywords": [],
      "category": "X热点",
      "slug": "20260529-just-in-ethereum0x514910771af9ca656af840dff83e8264ecf986ca-futures-now-trade-247",
      "localUrl": "/news/20260529-just-in-ethereum0x514910771af9ca656af840dff83e8264ecf986ca-futures-now-trade-247.html"
    },
    {
      "source": "Decrypt",
      "title": "'He’s Full of Shit': JP Morgan's Jamie Dimon Takes Aim at Coinbase CEO Over Clarity Act",
      "summary": "Dimon vowed to fight the passage of the crypto market structure bill until the bitter end.",
      "url": "https://decrypt.co/369525/jp-morgan-ceo-jamie-dimon-takes-aim-coinbase-clarity-act",
      "publishedAt": "2026-05-29T21:24:28.000Z",
      "keywords": [
        "Business"
      ],
      "category": "市场",
      "slug": "20260529-hes-full-of-shit-jp-morgans-jamie-dimon-takes-aim-at-coinbase-ceo-over-clarity-a",
      "localUrl": "/news/20260529-hes-full-of-shit-jp-morgans-jamie-dimon-takes-aim-at-coinbase-ceo-over-clarity-a.html"
    },
    {
      "source": "X Wire",
      "title": "Bitcoin adoption continues to accelerate globally, with strong momentum shaping its next growth phase. New waves of demand are reinforcing Bitcoin’s expanding global footprint. ₿ - x.com",
      "summary": "<a href=\"https://news.google.com/rss/articles/CBMiXEFVX3lxTE0yWnoxeUhBeXgzdTRQakNQZllxVmhqQlRGWC1sTVFNbE5HM290SnlrVDhZYW1qcTAwNUJVdzlDOE1aUVhKRHhHd3B1V19ZZXlXUlpYZk0yTEN1bm1Q?oc=5\" target=\"_blank\">Bitcoin adoption continues to accelerate g…",
      "url": "https://news.google.com/rss/articles/CBMiXEFVX3lxTE0yWnoxeUhBeXgzdTRQakNQZllxVmhqQlRGWC1sTVFNbE5HM290SnlrVDhZYW1qcTAwNUJVdzlDOE1aUVhKRHhHd3B1V19ZZXlXUlpYZk0yTEN1bm1Q?oc=5",
      "publishedAt": "2026-05-29T21:01:14.000Z",
      "keywords": [],
      "category": "X热点",
      "slug": "20260529-bitcoin-adoption-continues-to-accelerate-globally-with-strong-momentum-shaping-i",
      "localUrl": "/news/20260529-bitcoin-adoption-continues-to-accelerate-globally-with-strong-momentum-shaping-i.html"
    },
    {
      "source": "Decrypt",
      "title": "Treasury Secretary Bessent Says US Has 'Grabbed' $1 Billion in Crypto From Iran",
      "summary": "Treasury Secretary Scott Bessent said the U.S. has \"outright grabbed\" roughly $1 billion worth of cryptocurrencies from Iran via seizures.",
      "url": "https://decrypt.co/369522/treasurys-bessent-says-us-grabbed-1-billion-crypto-iran",
      "publishedAt": "2026-05-29T20:40:37.000Z",
      "keywords": [
        "Law and Order"
      ],
      "category": "监管",
      "slug": "20260529-treasury-secretary-bessent-says-us-has-grabbed-1-billion-in-crypto-from-iran",
      "localUrl": "/news/20260529-treasury-secretary-bessent-says-us-has-grabbed-1-billion-in-crypto-from-iran.html"
    },
    {
      "source": "Decrypt",
      "title": "Celsius Founder Alex Mashinsky Files to Have 12-Year Crypto Fraud Sentence Vacated",
      "summary": "Celsius founder and former CEO Alex Mashinsky hopes to have his prison sentence vacated, claiming a legal conflict tied to Sam Bankman-Fried.",
      "url": "https://decrypt.co/369520/celsius-founder-mashinsky-files-12-year-crypto-fraud-sentence-vacated",
      "publishedAt": "2026-05-29T20:28:18.000Z",
      "keywords": [
        "celsius-degree-token",
        "Law and Order"
      ],
      "category": "监管",
      "slug": "20260529-celsius-founder-alex-mashinsky-files-to-have-12-year-crypto-fraud-sentence-vacat",
      "localUrl": "/news/20260529-celsius-founder-alex-mashinsky-files-to-have-12-year-crypto-fraud-sentence-vacat.html"
    },
    {
      "source": "Decrypt",
      "title": "Coinbase Becomes First US Exchange Allowed to Offer Global Crypto Perps Trading",
      "summary": "Coinbase can offer U.S. customers access to offshore crypto perpetual futures, a risky form of leveraged crypto trading, the CFTC said Friday.",
      "url": "https://decrypt.co/369504/coinbase-first-us-exchange-allowed-offer-global-crypto-perps-trading",
      "publishedAt": "2026-05-29T19:41:34.000Z",
      "keywords": [
        "Law and Order"
      ],
      "category": "监管",
      "slug": "20260529-coinbase-becomes-first-us-exchange-allowed-to-offer-global-crypto-perps-trading",
      "localUrl": "/news/20260529-coinbase-becomes-first-us-exchange-allowed-to-offer-global-crypto-perps-trading.html"
    },
    {
      "source": "Decrypt",
      "title": "Lenovo Stock Doubles in May on AI Server Boom—Best Month in 27 Years",
      "summary": "The world's biggest PC maker surged 109% in May after AI revenue hit 38% of quarterly sales. Goldman Sachs more than doubled its target.",
      "url": "https://decrypt.co/369505/lenovo-stock-doubles-may-ai-server-boom",
      "publishedAt": "2026-05-29T19:34:26.000Z",
      "keywords": [
        "Markets"
      ],
      "category": "市场",
      "slug": "20260529-lenovo-stock-doubles-in-may-on-ai-server-boombest-month-in-27-years",
      "localUrl": "/news/20260529-lenovo-stock-doubles-in-may-on-ai-server-boombest-month-in-27-years.html"
    },
    {
      "source": "X Wire",
      "title": "#Bitcoin crashing down in the final days of the month is relatively standard. Almost every month in 2026, it's up only until the 14-17th, and then we're going back down for the remainder of the month. May isn't different. The only difference: some altcoins have sh - x.com",
      "summary": "<a href=\"https://news.google.com/rss/articles/CBMiY0FVX3lxTE5PQm1NUE1UdXpWMml3eVlaVHo1SkduekM0aTh3M2lqaUhtbDlKRTVrMHgySkpBcTdwY0Q1cVJMUS1yZ2ZEeGdDTGwxSm5wTlpVbzBmMzdiUUs0eWZKdTh3cDFJNA?oc=5\" target=\"_blank\">#Bitcoin crashing down in the fi…",
      "url": "https://news.google.com/rss/articles/CBMiY0FVX3lxTE5PQm1NUE1UdXpWMml3eVlaVHo1SkduekM0aTh3M2lqaUhtbDlKRTVrMHgySkpBcTdwY0Q1cVJMUS1yZ2ZEeGdDTGwxSm5wTlpVbzBmMzdiUUs0eWZKdTh3cDFJNA?oc=5",
      "publishedAt": "2026-05-29T18:55:00.000Z",
      "keywords": [],
      "category": "X热点",
      "slug": "20260529-bitcoin-crashing-down-in-the-final-days-of-the-month-is-relatively-standard-almo",
      "localUrl": "/news/20260529-bitcoin-crashing-down-in-the-final-days-of-the-month-is-relatively-standard-almo.html"
    },
    {
      "source": "Decrypt",
      "title": "You Can Now Read the US Constitution via the Bitcoin Blockchain",
      "summary": "One of America's most important historical documents will forever be inscribed on a Bitcoin block, thanks to someone's $83 transaction fee.",
      "url": "https://decrypt.co/369498/you-can-read-us-constitution-bitcoin-blockchain",
      "publishedAt": "2026-05-29T18:31:11.000Z",
      "keywords": [
        "Technology"
      ],
      "category": "市场",
      "slug": "20260529-you-can-now-read-the-us-constitution-via-the-bitcoin-blockchain",
      "localUrl": "/news/20260529-you-can-now-read-the-us-constitution-via-the-bitcoin-blockchain.html"
    },
    {
      "source": "Decrypt",
      "title": "NYSE Parent Isn't 'Freaked Out' by Hyperliquid—It's Learning From the Crypto Perps Giant",
      "summary": "Intercontinental Exchange CEO Jeffrey Sprecher said his company and Hyperliquid are learning from each other as crypto perps gain ground.",
      "url": "https://decrypt.co/369497/nyse-parent-isnt-freaked-out-hyperliquid-learning-crypto-perps",
      "publishedAt": "2026-05-29T18:14:59.000Z",
      "keywords": [
        "Business"
      ],
      "category": "综合",
      "slug": "20260529-nyse-parent-isnt-freaked-out-by-hyperliquidits-learning-from-the-crypto-perps-gi",
      "localUrl": "/news/20260529-nyse-parent-isnt-freaked-out-by-hyperliquidits-learning-from-the-crypto-perps-gi.html"
    },
    {
      "source": "X Wire",
      "title": "The current drama around the Ethereum Foundation (EF) and the noise around the price of ETH are missing the big picture. While I genuinely understand this debate, it will not determine who leads the next decade of financial infrastructure.This is one stakehol - x.com",
      "summary": "<a href=\"https://news.google.com/rss/articles/CBMiX0FVX3lxTE1SaHBOWUluSXlSbW16MUhWNVdPZlhEeXdJUG5jeTZLLW9sZmFUb0ZBdDUyc2RVVlJySHRLTHJKRlU5ZHJldHo3aWxScXpKXzhGUmtDZ1JVdlRTQmc2YThN?oc=5\" target=\"_blank\">The current drama around the Ethereum …",
      "url": "https://news.google.com/rss/articles/CBMiX0FVX3lxTE1SaHBOWUluSXlSbW16MUhWNVdPZlhEeXdJUG5jeTZLLW9sZmFUb0ZBdDUyc2RVVlJySHRLTHJKRlU5ZHJldHo3aWxScXpKXzhGUmtDZ1JVdlRTQmc2YThN?oc=5",
      "publishedAt": "2026-05-29T17:45:08.000Z",
      "keywords": [],
      "category": "X热点",
      "slug": "20260529-the-current-drama-around-the-ethereum-foundation-ef-and-the-noise-around-the-pri",
      "localUrl": "/news/20260529-the-current-drama-around-the-ethereum-foundation-ef-and-the-noise-around-the-pri.html"
    },
    {
      "source": "Decrypt",
      "title": "AI Models Can’t Agree on Basic Facts Most of the Time, Study Shows",
      "summary": "A new study gave five frontier AI models 1,000 real-world claims to fact-check. They disagreed on 67% of them.",
      "url": "https://decrypt.co/369480/ai-models-disagree-fact-checking-two-thirds-study",
      "publishedAt": "2026-05-29T17:26:24.000Z",
      "keywords": [
        "Artificial Intelligence"
      ],
      "category": "综合",
      "slug": "20260529-ai-models-cant-agree-on-basic-facts-most-of-the-time-study-shows",
      "localUrl": "/news/20260529-ai-models-cant-agree-on-basic-facts-most-of-the-time-study-shows.html"
    },
    {
      "source": "Decrypt",
      "title": "Wintermute Is Providing Liquidity on Kalshi and Polymarket, Linking Two Giants",
      "summary": "Wintermute is providing liquidity on the two biggest prediction markets, linking flows for both firms, according to a source familiar with the matter.",
      "url": "https://decrypt.co/369475/wintermute-liquidity-kalshi-polymarket-prediction-markets",
      "publishedAt": "2026-05-29T16:20:08.000Z",
      "keywords": [
        "Business"
      ],
      "category": "DeFi",
      "slug": "20260529-wintermute-is-providing-liquidity-on-kalshi-and-polymarket-linking-two-giants",
      "localUrl": "/news/20260529-wintermute-is-providing-liquidity-on-kalshi-and-polymarket-linking-two-giants.html"
    },
    {
      "source": "Decrypt",
      "title": "CFTC Approves Bitcoin Perpetual Futures on Prediction Market Kalshi",
      "summary": "The CFTC issued an order allowing Kalshi to offer perpetual futures in the U.S., starting with contracts tied to Bitcoin's price.",
      "url": "https://decrypt.co/369465/cftc-approves-bitcoin-perpetual-futures-kalshi",
      "publishedAt": "2026-05-29T15:00:50.000Z",
      "keywords": [
        "Business"
      ],
      "category": "市场",
      "slug": "20260529-cftc-approves-bitcoin-perpetual-futures-on-prediction-market-kalshi",
      "localUrl": "/news/20260529-cftc-approves-bitcoin-perpetual-futures-on-prediction-market-kalshi.html"
    },
    {
      "source": "Decrypt",
      "title": "Sui Network Goes Down for Second Straight Day as Weekly Token Slide Hits 20%",
      "summary": "The Sui token is among the worst performing top 100 crypto assets of the last week in the wake of back-to-back outages.",
      "url": "https://decrypt.co/369464/sui-network-goes-down-second-straight-day-weekly-token-slide",
      "publishedAt": "2026-05-29T14:42:01.000Z",
      "keywords": [
        "Markets"
      ],
      "category": "监管",
      "slug": "20260529-sui-network-goes-down-for-second-straight-day-as-weekly-token-slide-hits-20",
      "localUrl": "/news/20260529-sui-network-goes-down-for-second-straight-day-as-weekly-token-slide-hits-20.html"
    },
    {
      "source": "X Wire",
      "title": "Regulated crypto options and perps are coming to @Coinbase for US customers. A massive first for the industry, thanks to the @CFTC and Chairman @MichaelSelig’s commitment to US innovation. We’re bringing proven global products under American regul - x.com",
      "summary": "<a href=\"https://news.google.com/rss/articles/CBMiZEFVX3lxTE9HSXlWeHREZmRoLXFVNmZ3VTNnT3pEempZdnpYZXdOMnRVanR1WmhwS2hFdkc2NjBvdUpXQ1hCT0R4ZkJheXhEd1cwdTdPcl9ydEFVdk1XeDBnQ2lSTmhqOVFlVkI?oc=5\" target=\"_blank\">Regulated crypto options and pe…",
      "url": "https://news.google.com/rss/articles/CBMiZEFVX3lxTE9HSXlWeHREZmRoLXFVNmZ3VTNnT3pEempZdnpYZXdOMnRVanR1WmhwS2hFdkc2NjBvdUpXQ1hCT0R4ZkJheXhEd1cwdTdPcl9ydEFVdk1XeDBnQ2lSTmhqOVFlVkI?oc=5",
      "publishedAt": "2026-05-29T14:19:13.000Z",
      "keywords": [],
      "category": "X热点",
      "slug": "20260529-regulated-crypto-options-and-perps-are-coming-to-coinbase-for-us-customers-a-mas",
      "localUrl": "/news/20260529-regulated-crypto-options-and-perps-are-coming-to-coinbase-for-us-customers-a-mas.html"
    },
    {
      "source": "X Wire",
      "title": "We're bringing global crypto derivatives to the U.S. Coinbase is the first regulated company to bring global crypto options & perpetual futures to the States, thanks to @CFTC. → Tap the deepest crypto options & perps liquidity → Access >$31B BTC options OI vi - x.com",
      "summary": "<a href=\"https://news.google.com/rss/articles/CBMiXkFVX3lxTE5hblJGS292UzR5WTdmOU1PRXVJWWhNOWwwR0VjblN0blU0NFVsODZIcWhkYlNabUVyWXM2RVZmUHZ4V01mYXdWQzJIaEJDWUEyWnE3OE1PMllyc0dBN3c?oc=5\" target=\"_blank\">We're bringing global crypto derivative…",
      "url": "https://news.google.com/rss/articles/CBMiXkFVX3lxTE5hblJGS292UzR5WTdmOU1PRXVJWWhNOWwwR0VjblN0blU0NFVsODZIcWhkYlNabUVyWXM2RVZmUHZ4V01mYXdWQzJIaEJDWUEyWnE3OE1PMllyc0dBN3c?oc=5",
      "publishedAt": "2026-05-29T14:11:18.000Z",
      "keywords": [],
      "category": "X热点",
      "slug": "20260529-were-bringing-global-crypto-derivatives-to-the-us-coinbase-is-the-first-regulate",
      "localUrl": "/news/20260529-were-bringing-global-crypto-derivatives-to-the-us-coinbase-is-the-first-regulate.html"
    },
    {
      "source": "X Wire",
      "title": "Commission Staff Confirms the Categorization of Certain Crypto Asset Perpetuals as Foreign Futures and Issues No-Action Letter Regarding FCM Transfers of Customer Crypto Assets to Foreign Brokers as Margin: - x.com",
      "summary": "<a href=\"https://news.google.com/rss/articles/CBMiWEFVX3lxTE5mNGRGZlRVd3BGRVRVNldlV1FPdjN5ZGR5YVpnemRrd0J0VXg4UzlMUlpqWUQtZFpjRkxhbzBRdENrMl9vTlNKellzT1BhblVFOW1VVHM3YWM?oc=5\" target=\"_blank\">Commission Staff Confirms the Categorization of…",
      "url": "https://news.google.com/rss/articles/CBMiWEFVX3lxTE5mNGRGZlRVd3BGRVRVNldlV1FPdjN5ZGR5YVpnemRrd0J0VXg4UzlMUlpqWUQtZFpjRkxhbzBRdENrMl9vTlNKellzT1BhblVFOW1VVHM3YWM?oc=5",
      "publishedAt": "2026-05-29T14:08:09.000Z",
      "keywords": [],
      "category": "X热点",
      "slug": "20260529-commission-staff-confirms-the-categorization-of-certain-crypto-asset-perpetuals-",
      "localUrl": "/news/20260529-commission-staff-confirms-the-categorization-of-certain-crypto-asset-perpetuals-.html"
    },
    {
      "source": "X Wire",
      "title": "JUST IN: Someone publishes the entire U.S. Constitution on the Bitcoin blockchain 🇺🇸 - x.com",
      "summary": "<a href=\"https://news.google.com/rss/articles/CBMiZ0FVX3lxTFB5VFdsUVpMOFhTRlR4ZWRlRmhlVWtRcVRBQjdNODNMWnFXV1N3V2MzVUVNYjhWMDUxdmNaY3A5MzcxdnVRX1lpMVNQRldCTW95V1U5ZVF1MnZid0xKbnFQTkpsc1BabG8?oc=5\" target=\"_blank\">JUST IN: Someone publishes …",
      "url": "https://news.google.com/rss/articles/CBMiZ0FVX3lxTFB5VFdsUVpMOFhTRlR4ZWRlRmhlVWtRcVRBQjdNODNMWnFXV1N3V2MzVUVNYjhWMDUxdmNaY3A5MzcxdnVRX1lpMVNQRldCTW95V1U5ZVF1MnZid0xKbnFQTkpsc1BabG8?oc=5",
      "publishedAt": "2026-05-29T13:14:24.000Z",
      "keywords": [],
      "category": "X热点",
      "slug": "20260529-just-in-someone-publishes-the-entire-us-constitution-on-the-bitcoin-blockchain-x",
      "localUrl": "/news/20260529-just-in-someone-publishes-the-entire-us-constitution-on-the-bitcoin-blockchain-x.html"
    },
    {
      "source": "Decrypt",
      "title": "Bitcoin ETFs Shed $2.8B in Record-Breaking Nine-Day Streak",
      "summary": "Cooling demand for Bitcoin ETFs adds to declining accumulation by whales, underscoring a trying time for the crypto market.",
      "url": "https://decrypt.co/369449/bitcoin-etfs-shed-2-8b-in-record-breaking-nine-day-streak",
      "publishedAt": "2026-05-29T12:39:29.000Z",
      "keywords": [
        "Coins"
      ],
      "category": "监管",
      "slug": "20260529-bitcoin-etfs-shed-28b-in-record-breaking-nine-day-streak",
      "localUrl": "/news/20260529-bitcoin-etfs-shed-28b-in-record-breaking-nine-day-streak.html"
    },
    {
      "source": "Decrypt",
      "title": "Morning Minute: Hyperliquid Is 'Bigger Than Nasdaq'",
      "summary": "The man who built the modern NYSE just said Hyperliquid is bigger than Nasdaq. JPMorgan says the debasement trade is unwinding.",
      "url": "https://decrypt.co/369444/morning-minute-hyperliquid-is-bigger-than-nasdaq",
      "publishedAt": "2026-05-29T12:08:19.000Z",
      "keywords": [
        "Opinion"
      ],
      "category": "综合",
      "slug": "20260529-morning-minute-hyperliquid-is-bigger-than-nasdaq",
      "localUrl": "/news/20260529-morning-minute-hyperliquid-is-bigger-than-nasdaq.html"
    }
  ]
}
